safeguard/__init__.py
safeguard/exceptions.py
safeguard/helper/__init__.py
safeguard/helper/base_container.py
safeguard/helper/immutable.py
safeguard/maybe.py
safeguard/py.typed
safeguard/result.py
safeguard-0.1.0.dist-info/LICENSE
safeguard-0.1.0.dist-info/METADATA
safeguard-0.1.0.dist-info/WHEEL
safeguard-0.1.0.dist-info/RECORD
