Metadata-Version: 2.1
Name: safeguard
Version: 0.1.0
Summary: Railway Oriented Programming Library
License: MIT
Keywords: result,maybe,railway-oriented-programming,functional-programming,safeguard
Author: Demetre Dzmanashvili
Author-email: demetredzmanashvili@gmail.com
Requires-Python: >=3.9,<4.0
Classifier: Development Status :: 4 - Beta
Classifier: License :: OSI Approved :: MIT License
Classifier: Programming Language :: Python :: 3
Classifier: Programming Language :: Python :: 3.9
Classifier: Programming Language :: Python :: 3.10
Classifier: Programming Language :: Python :: 3.11
Classifier: Programming Language :: Python :: 3.12
Classifier: Programming Language :: Python :: 3 :: Only
